{
  "login": {
    "title": "Fincept-এ স্বাগতম",
    "subtitle": "আপনার আর্থিক টার্মিনালে অ্যাক্সেস করতে সাইন ইন করুন।",
    "emailLabel": "ইমেইল ঠিকানা",
    "passwordLabel": "পাসওয়ার্ড",
    "loginButton": "সাইন ইন",
    "signingIn": "সাইন ইন হচ্ছে...",
    "guestButton": "অতিথি হিসেবে চালিয়ে যান",
    "forgotPassword": "পাসওয়ার্ড ভুলে গেছেন?",
    "noAccount": "অ্যাকাউন্ট নেই?",
    "signUp": "সাইন আপ"
  },
  "register": {
    "title": "অ্যাকাউন্ট তৈরি করুন",
    "subtitle": "পেশাদার আর্থিক টার্মিনালে অ্যাক্সেসের জন্য Fincept-এ যোগ দিন।",
    "firstNameLabel": "প্রথম নাম *",
    "lastNameLabel": "শেষ নাম *",
    "registerButton": "অ্যাকাউন্ট তৈরি করুন",
    "haveAccount": "ইতিমধ্যে অ্যাকাউন্ট আছে?",
    "signIn": "সাইন ইন"
  },
  "forgotPassword": {
    "title": "পাসওয়ার্ড রিসেট",
    "subtitle": "নির্দেশাবলী পেতে ইমেইল দিন",
    "sendButton": "লিংক পাঠান",
    "backToLogin": "লগইনে ফিরে যান"
  }
}