{
    "profile": "FINCEPT টার্মিনাল প্রোফাইল",
    "guestProfile": "FINCEPT টার্মিনাল অতিথি প্রোফাইল",
    "guestSession": "FinceptTerminal v3.0.11 | অতিথি সেশন",
    "requests": "অনুরোধ",
    "remaining": "অবশিষ্ট",
    "loading": "লোড হচ্ছে...",
    "refresh": "↻ রিফ্রেশ",
    "sessionInformation": "সেশন তথ্য",
    "accountType": "অ্যাকাউন্ট ধরন",
    "guest": "অতিথি",
    "sessionExpires": "সেশন মেয়াদ",
    "deviceId": "ডিভাইস আইডি",
    "apiKey": "API কী",
    "dailyUsageStats": "দৈনিক ব্যবহার পরিসংখ্যান",
    "todaysRequests": "আজকের অনুরোধ",
    "status": "স্থিতি",
    "active": "সক্রিয়",
    "upgradeToFullAccess": "সম্পূর্ণ অ্যাক্সেসে আপগ্রেড করুন",
    "createAccountUnlock": "আনলক করতে বিনামূল্যে অ্যাকাউন্ট তৈরি করুন",
    "unlimitedApiRequests": "সীমাহীন API অনুরোধ",
    "permanentApiKey": "স্থায়ী API কী",
    "allDatabaseAccess": "সমস্ত ডাটাবেস অ্যাক্সেস",
    "premiumFeatures": "প্রিমিয়াম বৈশিষ্ট্য এবং সরঞ্জাম",
    "dataMarketplace": "ডেটা মার্কেটপ্লেস",
    "advancedAnalytics": "উন্নত বিশ্লেষণ",
    "viewPricingPlans": "মূল্য পরিকল্পনা দেখুন",
    "device": "ডিভাইস",
    "updating": "আপডেট হচ্ছে",
    "ready": "প্রস্তুত",
    "credits": "ক্রেডিট"
}